LICENSE
README.md
setup.py
termite/__init__.py
termite/__main__.py
termite/termite.py
termite/dtos/Config.py
termite/dtos/Script.py
termite/dtos/__init__.py
termite/shared/__init__.py
termite/shared/call_llm.py
termite/shared/run_tui.py
termite/shared/utils/__init__.py
termite/shared/utils/fix_imports.py
termite/shared/utils/python_exe.py
termite/shared/utils/run_pty.py
termite/tools/__init__.py
termite/tools/build_tui.py
termite/tools/design_tui.py
termite/tools/fix_errors.py
termite/tools/refine.py
termite_ai.egg-info/PKG-INFO
termite_ai.egg-info/SOURCES.txt
termite_ai.egg-info/dependency_links.txt
termite_ai.egg-info/entry_points.txt
termite_ai.egg-info/requires.txt
termite_ai.egg-info/top_level.txt